LICENSE
MANIFEST.in
README.rst
setup.cfg
setup.py
databuild_lua/__init__.py
databuild_lua/lua.py
databuild_lua.egg-info/PKG-INFO
databuild_lua.egg-info/SOURCES.txt
databuild_lua.egg-info/dependency_links.txt
databuild_lua.egg-info/requires.txt
databuild_lua.egg-info/top_level.txt
databuild_lua/tests/__init__.py
databuild_lua/tests/test_environment.py