Metadata-Version: 1.1
Name: databuild-lua
Version: 0.0.3
Summary: Lua Environment Plugin for Databuild
Home-page: https://github.com/databuild/databuild-lua
Author: Flavio Curella
Author-email: flavio.curella@gmail.com
License: BSD
Platform: UNKNOWN
Classifier: Development Status :: 4 - Beta
Classifier: Environment :: Console
Classifier: Intended Audience :: Science/Research
Classifier: License :: OSI Approved :: BSD License
Classifier: Operating System :: OS Independent
Classifier: Programming Language :: Python :: 2.7
Classifier: Programming Language :: Python :: 3.2
Classifier: Programming Language :: Python :: 3.3
Classifier: Topic :: Scientific/Engineering :: Information Analysis
